curl/__init__.py
r2c/__init__.py
requests_to_curl/__init__.py
requests_to_curl/requests_to_curl.py
requests_to_curl/test.py
requests_to_curl-1.0.6.dist-info/LICENSE
requests_to_curl-1.0.6.dist-info/METADATA
requests_to_curl-1.0.6.dist-info/WHEEL
requests_to_curl-1.0.6.dist-info/top_level.txt
requests_to_curl-1.0.6.dist-info/RECORD
